hyko/__init__.py
hyko-0.1.0.dist-info/METADATA
hyko-0.1.0.dist-info/WHEEL
hyko-0.1.0.dist-info/RECORD
