Metadata-Version: 2.1
Name: hyko
Version: 0.1.0
Summary: hyko python sdk
Author: Ouassim Abdelmalek Ghribi
Author-email: oag@big-mama.io
Requires-Python: >=3.11,<4.0
Classifier: Programming Language :: Python :: 3
Classifier: Programming Language :: Python :: 3.11
Classifier: Programming Language :: Python :: 3.12
